<PAMDataset>
  <PAMRasterBand band="1">
    <Metadata>
      <MDI key="STATISTICS_APPROXIMATE">YES</MDI>
      <MDI key="STATISTICS_MINIMUM">0</MDI>
      <MDI key="STATISTICS_MAXIMUM">255</MDI>
      <MDI key="STATISTICS_MEAN">200.23027349471</MDI>
      <MDI key="STATISTICS_STDDEV">51.692971410598</MDI>
      <MDI key="STATISTICS_VALID_PERCENT">99.77</MDI>
    </Metadata>
  </PAMRasterBand>
  <PAMRasterBand band="2">
    <Metadata>
      <MDI key="STATISTICS_APPROXIMATE">YES</MDI>
      <MDI key="STATISTICS_MINIMUM">30</MDI>
      <MDI key="STATISTICS_MAXIMUM">255</MDI>
      <MDI key="STATISTICS_MEAN">219.01030598386</MDI>
      <MDI key="STATISTICS_STDDEV">40.311727394706</MDI>
      <MDI key="STATISTICS_VALID_PERCENT">99.77</MDI>
    </Metadata>
  </PAMRasterBand>
  <PAMRasterBand band="3">
    <Metadata>
      <MDI key="STATISTICS_APPROXIMATE">YES</MDI>
      <MDI key="STATISTICS_MINIMUM">31</MDI>
      <MDI key="STATISTICS_MAXIMUM">255</MDI>
      <MDI key="STATISTICS_MEAN">223.01155761498</MDI>
      <MDI key="STATISTICS_STDDEV">50.582642660194</MDI>
      <MDI key="STATISTICS_VALID_PERCENT">99.77</MDI>
    </Metadata>
  </PAMRasterBand>
  <PAMRasterBand band="4">
    <Metadata>
      <MDI key="STATISTICS_APPROXIMATE">YES</MDI>
      <MDI key="STATISTICS_MINIMUM">0</MDI>
      <MDI key="STATISTICS_MAXIMUM">255</MDI>
      <MDI key="STATISTICS_MEAN">254.41056910569</MDI>
      <MDI key="STATISTICS_STDDEV">12.245711464411</MDI>
      <MDI key="STATISTICS_VALID_PERCENT">100</MDI>
    </Metadata>
  </PAMRasterBand>
</PAMDataset>
